{
  "schema": "flyto.open-core-export.v1",
  "generated_at": "2026-07-16T15:19:37.228632+00:00",
  "source_workspace": "/Users/chester/flytohub",
  "source_manifest": "/Users/chester/flytohub/flyto-engine/release/config/flyto2/open-core-manifest.json",
  "package_name": "flyto2-warroom-ce",
  "release": {
    "name": "flyto2-warroom-ce",
    "display_name": "Flyto2 Warroom CE",
    "generate": [
      "warroom-ce-installer"
    ],
    "public_image_repository": "docker.io/chesterhsu/flyto-warroom",
    "public_images": {
      "engine": "docker.io/chesterhsu/flyto-warroom",
      "worker": "docker.io/chesterhsu/flyto-warroom",
      "frontend": "docker.io/chesterhsu/flyto-warroom",
      "runner": "docker.io/chesterhsu/flyto-warroom",
      "verification": "docker.io/chesterhsu/flyto-warroom",
      "brand_vision": "docker.io/chesterhsu/flyto-warroom",
      "pdf": "docker.io/chesterhsu/flyto-warroom"
    },
    "public_image_tags": {
      "engine": "engine-ce",
      "worker": "worker-ce",
      "frontend": "code-ce",
      "runner": "runner-ce",
      "verification": "verification-ce",
      "brand_vision": "brand-vision-ce",
      "pdf": "pdf-ce"
    },
    "public_image_digests": {
      "engine": "sha256:4ba0700b45ab7e5f5c70b4764a36ffcbf5722e7ae4147cfbf86cf0461f93ed33",
      "worker": "sha256:4ba0700b45ab7e5f5c70b4764a36ffcbf5722e7ae4147cfbf86cf0461f93ed33",
      "frontend": "sha256:f0ab307b8c38822a6202540caaa429f882f8100b641bbb09809437316a619eb0",
      "runner": "sha256:239744f8753365b4e82f08628a9964aa6364ce8d37823f92ad83dcf915d75774",
      "verification": "sha256:ae3f5da8571eb1ee877ec4baf8c0e430f91ff73a878f8e2eeb9b07aae0eb8a90",
      "brand_vision": "sha256:f83f2a3b3c3e3de9313077646c57c769d9ca303746d1d02312d808cbab5074ad",
      "pdf": "sha256:f428b27543a1745b2b9586260964f8bb2687e877aaf3a7491134c8a4d40e0889"
    }
  },
  "release_files": [
    "install/docker-compose.ce.yml",
    "install/docker-compose.ee-sim.yml",
    "install/.env.ce.example",
    "install/.env.ee-sim.example",
    "Makefile",
    ".flyto-rules.yaml",
    "install/scripts/build-local-images.sh",
    "install/scripts/hash-local-password.py",
    "install/scripts/setup-ce.py",
    "install/scripts/verify-docker-images.py",
    "install/scripts/preflight.py",
    "install/scripts/mint-ee-sim-jwt.py",
    "install/scripts/audit-release-tree.py",
    "docs/local-install.md",
    "docs/enterprise-simulation.md",
    "docs/enterprise-cloud-bridge.md",
    "docs/code-protection.md",
    "TRADEMARK.md",
    "SECURITY.md",
    "GOVERNANCE.md",
    "AGENTS.md",
    "docs/official-builds.md",
    "docs/account-security.md",
    "docs/docker-hub-overview.md",
    "docs/github-hardening.md",
    ".gitignore",
    "LICENSES.md",
    "DEPENDENCIES.md",
    "CONTRIBUTING.md",
    "LICENSE",
    "CLA.md",
    ".github/workflows/cla.yml",
    "docs/upstream-feedback-loop.md",
    "scripts/export-upstream-patches.py",
    ".github/CODEOWNERS",
    ".github/pull_request_template.md",
    "scripts/audit-github-protection.py",
    "scripts/audit-ce-boundary.py",
    ".github/workflows/ci.yml",
    ".env.example",
    "CHANGELOG.md",
    "docs/README.md",
    "docs/autofix-whitepaper.md",
    "docs/benchmark-evidence.md",
    "docs/cloud-bundle-producer.md",
    "docs/demo-seed-workspace.md",
    "docs/edition-profiles.md",
    "docs/feature-matrix.md",
    "docs/paid-prerequisites.md",
    "docs/public-roadmap.md",
    "docs/release-readiness.md",
    "install/README.md",
    "install/demo-workspace.json",
    "install/fixtures/cloud-bundle/bundle-template.yaml",
    "install/fixtures/cloud-bundle/recipes/flyto2-ui-login-smoke.yaml",
    "install/fixtures/cloud-bundle/recipes/flyto2-ui-smoke.yaml",
    "install/fixtures/cloud-bundle/recipes/warroom-deterministic-audit.yaml",
    "install/scripts/audit-docker-build-boundary.py",
    "install/scripts/build-cloud-bundle-fixture.py",
    "install/scripts/provider-readiness.py",
    "install/scripts/publish-multiarch-images.sh",
    "install/scripts/seed-demo-workspace.py",
    "install/tests/test_cloud_bundle_fixture.py",
    "install/tests/test_positioning_audit.py",
    "install/tests/test_provider_readiness.py",
    "packages/README.md",
    "scripts/README.md",
    "scripts/audit-positioning.py",
    "docs/feature-matrix.md",
    "install/edition-overlays.json"
  ],
  "packages": [
    {
      "name": "flyto-code",
      "repo": "flyto-code",
      "file_count": 1599,
      "generated_files": [
        "package.json",
        "package-lock.json",
        "Dockerfile",
        "LICENSE",
        ".env.example",
        "OPEN_CORE.md",
        "src-next/types/module-manifests/index.ts",
        "src-next/types/module-manifests/__tests__/moduleBoundaryContract.test.ts",
        "CE_SOURCE_BOUNDARY.md",
        "scripts/audit-edition-boundary.mjs",
        "scripts/audit-platform-loops.mjs",
        "scripts/audit-navbar-smoke-registry.mjs",
        "scripts/audit-saas-contract.mjs"
      ],
      "path": "packages/flyto-code"
    },
    {
      "name": "flyto-contracts",
      "repo": "flyto-engine",
      "file_count": 22,
      "generated_files": [
        "README.md",
        "schemas/capability.schema.json",
        "schemas/scanner-manifest.schema.json",
        "schemas/evidence-event.schema.json",
        "schemas/runner-callback.schema.json",
        "schemas/product-verification-scenario.schema.json",
        "schemas/audit-event.schema.json",
        "examples/scanner-manifest.yaml",
        "examples/runner-callback.json",
        "examples/evidence-event.json",
        "conformance/README.md",
        "conformance/validate.py",
        "sdk/typescript/src/index.ts",
        "sdk/python/flyto_contracts/__init__.py",
        "sdk/go/contracts/doc.go",
        "openapi/flyto-code-observed.openapi.json"
      ],
      "path": "packages/flyto-contracts"
    },
    {
      "name": "flyto-engine-ce",
      "repo": "flyto-engine",
      "file_count": 92,
      "generated_files": [
        "README.md",
        "go.mod",
        "go.sum",
        "LICENSE",
        "SOURCE_BOUNDARY.json"
      ],
      "path": "services/flyto-engine-ce"
    }
  ],
  "closed_source_boundaries": [
    "billing, entitlement mutation, commercial gates, and Stripe/offline-license adapters",
    "enterprise SSO/SAML/SCIM, legal hold, airgap installers, deployment edition internals",
    "darkweb, stealer-log, phishing-feed, commercial threat-intel, and proprietary correlation datasets",
    "cloud/container/runtime live remediation orchestration and customer connector credentials",
    "Flyto2 Cloud Enterprise Bridge services, entitlement signer, managed job execution plane, and hosted SaaS control plane",
    "AutoFix promotion, approval, rollback orchestration, and commercial AI proposal workflows",
    "hosted SaaS-only frontend configuration, private preview credentials, and enterprise image publishing metadata"
  ],
  "merge_contracts": [
    "OSS exports are generated artifacts; do not hand-edit generated community trees.",
    "Every package must declare source repo, license, include patterns, protected paths, and deny path patterns.",
    "Exporter fails closed on missing include patterns, missing required paths, protected path inclusion, and denied content markers.",
    "Community packages may call back into enterprise only through documented contracts, not private imports."
  ],
  "build_time_overlay_contract": {
    "schema": "flyto.open-core-build-overlay.v1",
    "runtime_source_pull_allowed": false,
    "runtime_source_pull_reason": "Enterprise and SaaS builds must be reproducible, signed, offline-capable, and auditable; source is resolved only at package/build time.",
    "base": {
      "public_repo": "https://github.com/flytohub/flyto-warroom",
      "public_package": "flyto2-warroom-ce",
      "pin_required": true,
      "accepted_ref_kinds": [
        "commit_sha"
      ],
      "upstream_merge_rule": "Change private flyto-engine/flyto-code first, export flyto-warroom CE, pin that CE commit, then apply private overlays for paid editions."
    },
    "profiles": [
      {
        "id": "community",
        "display_name": "Flyto2 Warroom CE",
        "license_tier": "community",
        "edition": "ce",
        "base": "flyto-warroom@commit_sha",
        "include_packages": [
          "flyto-code",
          "flyto-contracts",
          "flyto-engine-ce"
        ],
        "allowed_module_editions": [
          "ce"
        ],
        "forbidden_moats": [
          "commercial-intel",
          "enterprise-control-plane",
          "managed-remediation",
          "saas-control-plane"
        ],
        "private_overlay_kinds": [],
        "entitlement_source": "local_ce_config"
      },
      {
        "id": "enterprise-onprem",
        "display_name": "Flyto2 Warroom Enterprise On-prem",
        "license_tier": "enterprise",
        "edition": "enterprise",
        "base": "flyto-warroom@commit_sha",
        "include_packages": [
          "flyto-code",
          "flyto-contracts",
          "flyto-engine-ce"
        ],
        "allowed_module_editions": [
          "ce",
          "enterprise"
        ],
        "forbidden_moats": [],
        "private_overlay_kinds": [
          "signed-license-gates",
          "sso-saml-scim",
          "legal-hold",
          "audit-retention",
          "enterprise-reporting"
        ],
        "entitlement_source": "signed_offline_or_online_license"
      },
      {
        "id": "enterprise-airgap",
        "display_name": "Flyto2 Warroom Enterprise Airgap",
        "license_tier": "enterprise",
        "edition": "enterprise",
        "base": "flyto-warroom@commit_sha",
        "include_packages": [
          "flyto-code",
          "flyto-contracts",
          "flyto-engine-ce"
        ],
        "allowed_module_editions": [
          "ce",
          "enterprise"
        ],
        "forbidden_moats": [],
        "private_overlay_kinds": [
          "offline-license",
          "airgap-installers",
          "offline-update-bundles",
          "signed-evidence-export"
        ],
        "entitlement_source": "offline_license_file"
      },
      {
        "id": "saas",
        "display_name": "Flyto2 Cloud / SaaS",
        "license_tier": "enterprise",
        "edition": "saas",
        "base": "flyto-warroom@commit_sha",
        "include_packages": [
          "flyto-code",
          "flyto-contracts",
          "flyto-engine-ce"
        ],
        "allowed_module_editions": [
          "ce",
          "enterprise",
          "saas"
        ],
        "forbidden_moats": [],
        "private_overlay_kinds": [
          "hosted-control-plane",
          "managed-runner-fleet",
          "commercial-intel-connectors",
          "managed-remediation"
        ],
        "entitlement_source": "hosted_control_plane"
      }
    ],
    "build_steps": [
      "Resolve and record the flyto-warroom CE commit SHA.",
      "Run open-core audit against the CE base before overlay.",
      "Apply private edition overlay selected by the signed license tier.",
      "Run capability, entitlement, audit-log, and release-boundary tests.",
      "Write release evidence with CE base commit, overlay profile, image digests, and verification results."
    ],
    "protected_overlay_kinds": [
      "commercial intelligence datasets",
      "hosted SaaS control plane",
      "enterprise license signer",
      "live cloud/container/runtime remediation adapters",
      "customer connector credentials",
      "enterprise SSO/SAML/SCIM implementation",
      "AutoFix AI proposal, approval, promotion, and rollback orchestration"
    ]
  },
  "frontend_source_boundary": {
    "schema": "flyto.frontend-open-core-boundary.v1",
    "source_repo": "flyto-code",
    "planned_public_package": "packages/flyto-code",
    "ce_export_mode": "ce_exportable_module_manifests_only",
    "non_exportable_module_manifests": [
      "src-next/types/module-manifests/enterprise.ts",
      "src-next/types/module-manifests/future.ts"
    ],
    "ce_pruned_paths": [
      "src-next/types/module-manifests/enterprise.ts",
      "src-next/types/module-manifests/future.ts",
      "src-next/app/(control-panel)/flyto/workspace/components/pages/EnterpriseControlPlanePage.tsx",
      "src-next/components/compounds/system/EnterpriseControlPlaneView.tsx",
      "src-next/components/compounds/system/__tests__/EnterpriseControlPlaneView.test.tsx"
    ],
    "ce_rewrite_files": [
      "src-next/types/module-manifests/index.ts",
      "src-next/types/module-manifests/__tests__/moduleBoundaryContract.test.ts"
    ],
    "ce_required_public_files": [
      "src-next/types/module-manifests/packageManifest.ts"
    ],
    "ce_allowed_contract_paths": [
      "src-next/lib/engine/system/enterprise.ts"
    ],
    "reason": "Private flyto-code keeps enterprise/future manifests for paid overlays; generated CE source keeps only routed CE-exportable modules and public API contracts."
  }
}
